{
	"name": "Pipeline 1",
	"properties": {
		"activities": [
			{
				"name": "Load Data to Azure Synapse",
				"type": "Copy",
				"dependsOn": [],
				"policy": {
					"timeout": "7.00:00:00",
					"retry": 0,
					"retryIntervalInSeconds": 30,
					"secureOutput": false,
					"secureInput": false
				},
				"userProperties": [],
				"typeProperties": {
					"source": {
						"type": "JsonSource",
						"storeSettings": {
							"type": "AzureBlobFSReadSettings",
							"recursive": true,
							"wildcardFileName": "*json",
							"enablePartitionDiscovery": false
						},
						"formatSettings": {
							"type": "JsonReadSettings"
						}
					},
					"sink": {
						"type": "SqlDWSink",
						"tableOption": "autoCreate",
						"disableMetricsCollection": false
					},
					"enableStaging": false,
					"translator": {
						"type": "TabularTranslator",
						"mappings": [
							{
								"source": {
									"path": "$['CompanyName']"
								},
								"sink": {
									"name": "CompanyName"
								}
							},
							{
								"source": {
									"path": "$['CustomerID']"
								},
								"sink": {
									"name": "CustomerID"
								}
							},
							{
								"source": {
									"path": "$['EmailAddress']"
								},
								"sink": {
									"name": "EmailAddress"
								}
							},
							{
								"source": {
									"path": "$['FirstName']"
								},
								"sink": {
									"name": "FirstName"
								}
							},
							{
								"source": {
									"path": "$['HashKey']"
								},
								"sink": {
									"name": "HashKey"
								}
							},
							{
								"source": {
									"path": "$['InsertedDate']"
								},
								"sink": {
									"name": "InsertedDate"
								}
							},
							{
								"source": {
									"path": "$['LastName']"
								},
								"sink": {
									"name": "LastName"
								}
							},
							{
								"source": {
									"path": "$['MiddleName']"
								},
								"sink": {
									"name": "MiddleName"
								}
							},
							{
								"source": {
									"path": "$['ModifiedDate']"
								},
								"sink": {
									"name": "ModifiedDate"
								}
							},
							{
								"source": {
									"path": "$['Phone']"
								},
								"sink": {
									"name": "Phone"
								}
							},
							{
								"source": {
									"path": "$['SalesPerson']"
								},
								"sink": {
									"name": "SalesPerson"
								}
							},
							{
								"source": {
									"path": "$['Suffix']"
								},
								"sink": {
									"name": "Suffix"
								}
							},
							{
								"source": {
									"path": "$['Title']"
								},
								"sink": {
									"name": "Title"
								}
							},
							{
								"source": {
									"path": "$['Full Name']"
								},
								"sink": {
									"name": "Full Name"
								}
							},
							{
								"source": {
									"path": "$['Customer Since']"
								},
								"sink": {
									"name": "Customer Since"
								}
							}
						]
					}
				},
				"inputs": [
					{
						"referenceName": "ADL_temp_customer_profile",
						"type": "DatasetReference"
					}
				],
				"outputs": [
					{
						"referenceName": "AzureSynapseDW",
						"type": "DatasetReference"
					}
				]
			}
		],
		"annotations": []
	}
}